foo/__init__.py
foo/models.py
foo/migrations/0001_initial.py
foo/migrations/__init__.py
typeform_feedback/__init__.py
typeform_feedback/admin.py
typeform_feedback/apps.py
typeform_feedback/conf.py
typeform_feedback/decorators.py
typeform_feedback/helpers.py
typeform_feedback/mixin.py
typeform_feedback/signals_define.py
typeform_feedback/urls.py
typeform_feedback/urls_webhooks.py
typeform_feedback/api/__init__.py
typeform_feedback/api/serializers.py
typeform_feedback/api/urls.py
typeform_feedback/api/views/__init__.py
typeform_feedback/api/views/generic_typeform.py
typeform_feedback/api/views/user_generic_typeform.py
typeform_feedback/migrations/0001_initial.py
typeform_feedback/migrations/0002_auto_20190925_0837.py
typeform_feedback/migrations/0003_auto_20191002_0621.py
typeform_feedback/migrations/0004_auto_20191002_0624.py
typeform_feedback/migrations/0005_usergenerictypeformfeedback_uuid.py
typeform_feedback/migrations/0006_auto_20191010_0814.py
typeform_feedback/migrations/0007_auto_20191014_0704.py
typeform_feedback/migrations/__init__.py
typeform_feedback/models/__init__.py
typeform_feedback/models/generic_typeform.py
typeform_feedback/models/user_generic_typeform.py
typeform_feedback/tasks/__init__.py
typeform_feedback/tasks/generic_typeform.py
typeform_feedback/tasks/mixin.py
typeform_feedback/templates/user_response_validation.html
typeform_feedback/views/__init__.py
typeform_feedback/views/generic_typeform.py
typeform_feedback/views/user_typeform.py
typeform_feedback/views/webhooks.py
django_typeform_feedback-0.2.5.dist-info/AUTHORS.rst
django_typeform_feedback-0.2.5.dist-info/LICENSE
django_typeform_feedback-0.2.5.dist-info/METADATA
django_typeform_feedback-0.2.5.dist-info/WHEEL
django_typeform_feedback-0.2.5.dist-info/top_level.txt
django_typeform_feedback-0.2.5.dist-info/RECORD
