Metadata-Version: 2.1
Name: django-typeform-feedback
Version: 0.2.5
Summary: Use typeform as feedback with Django
Home-page: https://github.com/exolever/django-typeform-feedback
Author: marfyl
Author-email: marfyl.dev@gmail.com
License: MIT
Keywords: python,django,typeform,feedback
Platform: UNKNOWN
Classifier: Development Status :: 5 - Production/Stable
Classifier: Environment :: Web Environment
Classifier: Framework :: Django :: 1.11
Classifier: Framework :: Django :: 2.0
Classifier: Intended Audience :: Developers
Classifier: License :: OSI Approved :: BSD License
Classifier: Natural Language :: English
Classifier: Operating System :: OS Independent
Classifier: Programming Language :: Python :: Implementation :: PyPy
Classifier: Programming Language :: Python
Classifier: Programming Language :: Python :: 3.6
Requires-Dist: celery
Requires-Dist: django
Requires-Dist: django-appconf
Requires-Dist: django-model-utils
Requires-Dist: djangorestframework
Requires-Dist: psycopg2-binary
Requires-Dist: redis
